mseep_cli/__init__.py
mseep_cli/server.py
mseep_cli-0.1.1.dist-info/METADATA
mseep_cli-0.1.1.dist-info/WHEEL
mseep_cli-0.1.1.dist-info/entry_points.txt
mseep_cli-0.1.1.dist-info/RECORD
